{
  "title": "Susan Manning",
  "source": "Wikipedia (Auto Fetch)",
  "source_url": "https://en.wikipedia.org/wiki/Susan_Manning",
  "content": "Susan Manning is a dance historian and Professor of English and Theatre at Northwestern University where she holds joint appointments in the English Department and Performance Studies.[1] She is currently chair of English at Northwestern.[2] Her first book, Ecstasy and the Demon, won the 1994 de la Torre Bueno Prize, while her second book, Modern Dance Negro Dance, received an Honorable Mention as Outstanding Publication from the Congress on Research in Dance. Manning has been the president of the Society of Dance History Scholars and is the convener for the Chicago Seminar on Dance and Performance.[2]\n\nManning graduated from Harvard College with a B.A. in 1978 (student-designed major in dance studies), and her Ph.D. from Columbia University (in 1987) in a cross-departmental program between English and Theatre.[3]\n\nThis article about someone associated with the art of dance is a stub. You can help Wikipedia by expanding it.\nThis biography of an American historian is a stub. You can help Wikipedia by expanding it.\nThis biography of an American English academic is a stub. You can help Wikipedia by expanding it.",
  "concepts": [
    "Susan Manning",
    "dance",
    "english",
    "wikipedia expanding",
    "wikipedia",
    "stub help",
    "stub",
    "manning",
    "help wikipedia",
    "help",
    "expanding"
  ],
  "findings": [
    "Publications",
    "References",
    "External links"
  ],
  "relationships": [
    {
      "subject": "Susan Manning",
      "relationship": "is a",
      "object": "dance historian and professor of english and theatre at northwestern university where she holds joint appointments in the english department and performance studies",
      "sentence": "Susan Manning is a dance historian and Professor of English and Theatre at Northwestern University where she holds joint appointments in the English Department and Performance Studies."
    }
  ],
  "timestamp": "2025-04-11T13:35:00.597798"
}